boldi/_webalbum_version.py
boldi/webalbum.py
boldi/webalbum/masonry.py
boldi/webalbum/templates/index.html.j2
boldi/webalbum/templates/masonry.html.j2
boldi/webalbum/templates/static/script.js
boldi/webalbum/templates/static/style.css
boldi_webalbum-0.9.7.dist-info/METADATA
boldi_webalbum-0.9.7.dist-info/WHEEL
boldi_webalbum-0.9.7.dist-info/RECORD
