Metadata-Version: 2.4
Name: boldi-webalbum
Version: 0.9.7
Summary: boldi.webalbum part of Boldi's Python libraries
Author-email: Boldizsár Palotás <boldizsar.palotas@gmail.com>
License: MIT
Requires-Python: >=3.12
Requires-Dist: jinja2
Requires-Dist: pillow
Requires-Dist: pydantic
Requires-Dist: pyexiftool
Requires-Dist: unidecode
